gtmediaspace-dl/__init__.py
gtmediaspace-dl/gtmediaspace-dl.py
gtmediaspace_dl/__init__.py
gtmediaspace_dl/gtmediaspace-dl.py
gtmediaspace_dl/gtmediaspace_dl.py
gtmediaspace_dl-0.0.1.dist-info/LICENSE
gtmediaspace_dl-0.0.1.dist-info/METADATA
gtmediaspace_dl-0.0.1.dist-info/WHEEL
gtmediaspace_dl-0.0.1.dist-info/entry_points.txt
gtmediaspace_dl-0.0.1.dist-info/top_level.txt
gtmediaspace_dl-0.0.1.dist-info/RECORD
